<?xml version="1.0" encoding="utf-8"?>
<edmx:Edmx Version="4.0" xmlns:edmx="http://docs.oasis-open.org/odata/ns/edmx">
    <edmx:Reference Uri="https://sap.github.io/odata-vocabularies/vocabularies/Common.xml">
        <edmx:Include Alias="Common" Namespace="com.sap.vocabularies.Common.v1"/>
    </edmx:Reference>
    <edmx:Reference Uri="https://oasis-tcs.github.io/odata-vocabularies/vocabularies/Org.OData.Core.V1.xml">
        <edmx:Include Alias="Core" Namespace="Org.OData.Core.V1"/>
    </edmx:Reference>
    <edmx:Reference Uri="https://sap.github.io/odata-vocabularies/vocabularies/UI.xml">
        <edmx:Include Alias="UI" Namespace="com.sap.vocabularies.UI.v1"/>
    </edmx:Reference>
    <edmx:DataServices>
        <Schema Namespace="SurveyService" xmlns="http://docs.oasis-open.org/odata/ns/edm">
            <EntityContainer Name="EntityContainer">
                <EntitySet Name="Questions" EntityType="SurveyService.Questions">
                    <NavigationPropertyBinding Path="question_type" Target="QuestionType"/>
                    <NavigationPropertyBinding Path="options" Target="Options"/>
                    <NavigationPropertyBinding Path="surveyForm" Target="SurveyForms"/>
                    <NavigationPropertyBinding Path="SiblingEntity" Target="Questions"/>
                </EntitySet>
                <EntitySet Name="Options" EntityType="SurveyService.Options">
                    <NavigationPropertyBinding Path="question" Target="Questions"/>
                    <NavigationPropertyBinding Path="SiblingEntity" Target="Options"/>
                </EntitySet>
                <EntitySet Name="Answers" EntityType="SurveyService.Answers">
                    <NavigationPropertyBinding Path="response" Target="Responses"/>
                    <NavigationPropertyBinding Path="question" Target="Questions"/>
                </EntitySet>
                <EntitySet Name="Responses" EntityType="SurveyService.Responses">
                    <NavigationPropertyBinding Path="answers" Target="Answers"/>
                    <NavigationPropertyBinding Path="surveyFormInstance" Target="SurveyFormInstances"/>
                </EntitySet>
                <EntitySet Name="SurveyForms" EntityType="SurveyService.SurveyForms">
                    <NavigationPropertyBinding Path="activation_status" Target="ActivationStatusType"/>
                    <NavigationPropertyBinding Path="Questions" Target="Questions"/>
                    <NavigationPropertyBinding Path="SiblingEntity" Target="SurveyForms"/>
                </EntitySet>
                <EntitySet Name="SurveyFormInstances" EntityType="SurveyService.SurveyFormInstances">
                    <NavigationPropertyBinding Path="filled_status" Target="FilledStatusType"/>
                    <NavigationPropertyBinding Path="region" Target="Regions"/>
                    <NavigationPropertyBinding Path="customer" Target="Customers"/>
                    <NavigationPropertyBinding Path="surveyForm" Target="SurveyForms"/>
                </EntitySet>
                <EntitySet Name="Regions" EntityType="SurveyService.Regions">
                    <NavigationPropertyBinding Path="customers" Target="Customers"/>
                </EntitySet>
                <EntitySet Name="Customers" EntityType="SurveyService.Customers">
                    <NavigationPropertyBinding Path="region" Target="Regions"/>
                </EntitySet>
                <EntitySet Name="QuestionType" EntityType="SurveyService.QuestionType">
                    <NavigationPropertyBinding Path="texts" Target="QuestionType_texts"/>
                    <NavigationPropertyBinding Path="localized" Target="QuestionType_texts"/>
                </EntitySet>
                <EntitySet Name="ActivationStatusType" EntityType="SurveyService.ActivationStatusType">
                    <NavigationPropertyBinding Path="texts" Target="ActivationStatusType_texts"/>
                    <NavigationPropertyBinding Path="localized" Target="ActivationStatusType_texts"/>
                </EntitySet>
                <EntitySet Name="FilledStatusType" EntityType="SurveyService.FilledStatusType">
                    <NavigationPropertyBinding Path="texts" Target="FilledStatusType_texts"/>
                    <NavigationPropertyBinding Path="localized" Target="FilledStatusType_texts"/>
                </EntitySet>
                <EntitySet Name="QuestionType_texts" EntityType="SurveyService.QuestionType_texts"/>
                <EntitySet Name="ActivationStatusType_texts" EntityType="SurveyService.ActivationStatusType_texts"/>
                <EntitySet Name="FilledStatusType_texts" EntityType="SurveyService.FilledStatusType_texts"/>
            </EntityContainer>
            <EntityType Name="Questions">
                <Key>
                    <PropertyRef Name="ID"/>
                    <PropertyRef Name="IsActiveEntity"/>
                </Key>
                <Property Name="createdAt" Type="Edm.DateTimeOffset" Precision="7"/>
                <Property Name="createdBy" Type="Edm.String" MaxLength="255"/>
                <Property Name="modifiedAt" Type="Edm.DateTimeOffset" Precision="7"/>
                <Property Name="modifiedBy" Type="Edm.String" MaxLength="255"/>
                <Property Name="ID" Type="Edm.Guid" Nullable="false"/>
                <Property Name="question_no" Type="Edm.Int32"/>
                <Property Name="question_label" Type="Edm.String"/>
                <NavigationProperty Name="question_type" Type="SurveyService.QuestionType">
                    <ReferentialConstraint Property="question_type_code" ReferencedProperty="code"/>
                </NavigationProperty>
                <Property Name="question_type_code" Type="Edm.String" MaxLength="20"/>
                <NavigationProperty Name="options" Type="Collection(SurveyService.Options)" Partner="question">
                    <OnDelete Action="Cascade"/>
                </NavigationProperty>
                <NavigationProperty Name="surveyForm" Type="SurveyService.SurveyForms" Partner="Questions">
                    <ReferentialConstraint Property="surveyForm_ID" ReferencedProperty="ID"/>
                </NavigationProperty>
                <Property Name="surveyForm_ID" Type="Edm.Guid"/>
                <Property Name="IsActiveEntity" Type="Edm.Boolean" Nullable="false" DefaultValue="true"/>
                <Property Name="HasActiveEntity" Type="Edm.Boolean" Nullable="false" DefaultValue="false"/>
                <Property Name="HasDraftEntity" Type="Edm.Boolean" Nullable="false" DefaultValue="false"/>
                <NavigationProperty Name="DraftAdministrativeData" Type="SurveyService.DraftAdministrativeData" ContainsTarget="true"/>
                <NavigationProperty Name="SiblingEntity" Type="SurveyService.Questions"/>
            </EntityType>
            <EntityType Name="Options">
                <Key>
                    <PropertyRef Name="ID"/>
                    <PropertyRef Name="IsActiveEntity"/>
                </Key>
                <Property Name="ID" Type="Edm.Guid" Nullable="false"/>
                <Property Name="createdAt" Type="Edm.DateTimeOffset" Precision="7"/>
                <Property Name="createdBy" Type="Edm.String" MaxLength="255"/>
                <Property Name="modifiedAt" Type="Edm.DateTimeOffset" Precision="7"/>
                <Property Name="modifiedBy" Type="Edm.String" MaxLength="255"/>
                <Property Name="option_label" Type="Edm.String"/>
                <Property Name="option_no" Type="Edm.Int32"/>
                <NavigationProperty Name="question" Type="SurveyService.Questions" Partner="options">
                    <ReferentialConstraint Property="question_ID" ReferencedProperty="ID"/>
                </NavigationProperty>
                <Property Name="question_ID" Type="Edm.Guid"/>
                <Property Name="IsActiveEntity" Type="Edm.Boolean" Nullable="false" DefaultValue="true"/>
                <Property Name="HasActiveEntity" Type="Edm.Boolean" Nullable="false" DefaultValue="false"/>
                <Property Name="HasDraftEntity" Type="Edm.Boolean" Nullable="false" DefaultValue="false"/>
                <NavigationProperty Name="DraftAdministrativeData" Type="SurveyService.DraftAdministrativeData" ContainsTarget="true"/>
                <NavigationProperty Name="SiblingEntity" Type="SurveyService.Options"/>
            </EntityType>
            <EntityType Name="Answers">
                <Key>
                    <PropertyRef Name="ID"/>
                </Key>
                <Property Name="ID" Type="Edm.Guid" Nullable="false"/>
                <Property Name="createdAt" Type="Edm.DateTimeOffset" Precision="7"/>
                <Property Name="createdBy" Type="Edm.String" MaxLength="255"/>
                <Property Name="modifiedAt" Type="Edm.DateTimeOffset" Precision="7"/>
                <Property Name="modifiedBy" Type="Edm.String" MaxLength="255"/>
                <Property Name="answer" Type="Edm.String"/>
                <NavigationProperty Name="response" Type="SurveyService.Responses" Partner="answers">
                    <ReferentialConstraint Property="response_ID" ReferencedProperty="ID"/>
                </NavigationProperty>
                <Property Name="response_ID" Type="Edm.Guid"/>
                <NavigationProperty Name="question" Type="SurveyService.Questions">
                    <ReferentialConstraint Property="question_ID" ReferencedProperty="ID"/>
                </NavigationProperty>
                <Property Name="question_ID" Type="Edm.Guid"/>
            </EntityType>
            <EntityType Name="Responses">
                <Key>
                    <PropertyRef Name="ID"/>
                </Key>
                <Property Name="ID" Type="Edm.Guid" Nullable="false"/>
                <Property Name="createdAt" Type="Edm.DateTimeOffset" Precision="7"/>
                <Property Name="createdBy" Type="Edm.String" MaxLength="255"/>
                <Property Name="modifiedAt" Type="Edm.DateTimeOffset" Precision="7"/>
                <Property Name="modifiedBy" Type="Edm.String" MaxLength="255"/>
                <NavigationProperty Name="answers" Type="Collection(SurveyService.Answers)" Partner="response"/>
                <NavigationProperty Name="surveyFormInstance" Type="SurveyService.SurveyFormInstances">
                    <ReferentialConstraint Property="surveyFormInstance_ID" ReferencedProperty="ID"/>
                </NavigationProperty>
                <Property Name="surveyFormInstance_ID" Type="Edm.Guid"/>
            </EntityType>
            <EntityType Name="SurveyForms">
                <Key>
                    <PropertyRef Name="ID"/>
                    <PropertyRef Name="IsActiveEntity"/>
                </Key>
                <Property Name="createdAt" Type="Edm.DateTimeOffset" Precision="7"/>
                <Property Name="createdBy" Type="Edm.String" MaxLength="255"/>
                <Property Name="modifiedAt" Type="Edm.DateTimeOffset" Precision="7"/>
                <Property Name="modifiedBy" Type="Edm.String" MaxLength="255"/>
                <Property Name="ID" Type="Edm.Guid" Nullable="false"/>
                <Property Name="survey_form_name" Type="Edm.String"/>
                <Property Name="survey_form_version" Type="Edm.Int32"/>
                <NavigationProperty Name="activation_status" Type="SurveyService.ActivationStatusType">
                    <ReferentialConstraint Property="activation_status_code" ReferencedProperty="code"/>
                </NavigationProperty>
                <Property Name="activation_status_code" Type="Edm.String" MaxLength="20"/>
                <NavigationProperty Name="Questions" Type="Collection(SurveyService.Questions)" Partner="surveyForm">
                    <OnDelete Action="Cascade"/>
                </NavigationProperty>
                <Property Name="IsActiveEntity" Type="Edm.Boolean" Nullable="false" DefaultValue="true"/>
                <Property Name="HasActiveEntity" Type="Edm.Boolean" Nullable="false" DefaultValue="false"/>
                <Property Name="HasDraftEntity" Type="Edm.Boolean" Nullable="false" DefaultValue="false"/>
                <NavigationProperty Name="DraftAdministrativeData" Type="SurveyService.DraftAdministrativeData" ContainsTarget="true"/>
                <NavigationProperty Name="SiblingEntity" Type="SurveyService.SurveyForms"/>
            </EntityType>
            <EntityType Name="SurveyFormInstances">
                <Key>
                    <PropertyRef Name="ID"/>
                </Key>
                <Property Name="ID" Type="Edm.Guid" Nullable="false"/>
                <Property Name="createdAt" Type="Edm.DateTimeOffset" Precision="7"/>
                <Property Name="createdBy" Type="Edm.String" MaxLength="255"/>
                <Property Name="modifiedAt" Type="Edm.DateTimeOffset" Precision="7"/>
                <Property Name="modifiedBy" Type="Edm.String" MaxLength="255"/>
                <Property Name="customer_email" Type="Edm.String"/>
                <Property Name="expiry_date" Type="Edm.Date"/>
                <Property Name="reminder_interval" Type="Edm.Int32"/>
                <NavigationProperty Name="filled_status" Type="SurveyService.FilledStatusType">
                    <ReferentialConstraint Property="filled_status_code" ReferencedProperty="code"/>
                </NavigationProperty>
                <Property Name="filled_status_code" Type="Edm.String" MaxLength="20"/>
                <NavigationProperty Name="region" Type="SurveyService.Regions">
                    <ReferentialConstraint Property="region_ID" ReferencedProperty="ID"/>
                </NavigationProperty>
                <Property Name="region_ID" Type="Edm.Guid"/>
                <NavigationProperty Name="customer" Type="SurveyService.Customers">
                    <ReferentialConstraint Property="customer_ID" ReferencedProperty="ID"/>
                </NavigationProperty>
                <Property Name="customer_ID" Type="Edm.Guid"/>
                <NavigationProperty Name="surveyForm" Type="SurveyService.SurveyForms">
                    <ReferentialConstraint Property="surveyForm_ID" ReferencedProperty="ID"/>
                </NavigationProperty>
                <Property Name="surveyForm_ID" Type="Edm.Guid"/>
            </EntityType>
            <EntityType Name="Regions">
                <Key>
                    <PropertyRef Name="ID"/>
                </Key>
                <Property Name="ID" Type="Edm.Guid" Nullable="false"/>
                <Property Name="createdAt" Type="Edm.DateTimeOffset" Precision="7"/>
                <Property Name="createdBy" Type="Edm.String" MaxLength="255"/>
                <Property Name="modifiedAt" Type="Edm.DateTimeOffset" Precision="7"/>
                <Property Name="modifiedBy" Type="Edm.String" MaxLength="255"/>
                <Property Name="region_name" Type="Edm.String"/>
                <NavigationProperty Name="customers" Type="Collection(SurveyService.Customers)" Partner="region"/>
            </EntityType>
            <EntityType Name="Customers">
                <Key>
                    <PropertyRef Name="ID"/>
                </Key>
                <Property Name="ID" Type="Edm.Guid" Nullable="false"/>
                <Property Name="createdAt" Type="Edm.DateTimeOffset" Precision="7"/>
                <Property Name="createdBy" Type="Edm.String" MaxLength="255"/>
                <Property Name="modifiedAt" Type="Edm.DateTimeOffset" Precision="7"/>
                <Property Name="modifiedBy" Type="Edm.String" MaxLength="255"/>
                <Property Name="customer_id" Type="Edm.String"/>
                <Property Name="customer_name" Type="Edm.String"/>
                <NavigationProperty Name="region" Type="SurveyService.Regions" Partner="customers">
                    <ReferentialConstraint Property="region_ID" ReferencedProperty="ID"/>
                </NavigationProperty>
                <Property Name="region_ID" Type="Edm.Guid"/>
            </EntityType>
            <EntityType Name="QuestionType">
                <Key>
                    <PropertyRef Name="code"/>
                </Key>
                <Property Name="name" Type="Edm.String" MaxLength="255"/>
                <Property Name="descr" Type="Edm.String" MaxLength="1000"/>
                <Property Name="code" Type="Edm.String" MaxLength="20" Nullable="false"/>
                <NavigationProperty Name="texts" Type="Collection(SurveyService.QuestionType_texts)">
                    <OnDelete Action="Cascade"/>
                </NavigationProperty>
                <NavigationProperty Name="localized" Type="SurveyService.QuestionType_texts">
                    <ReferentialConstraint Property="code" ReferencedProperty="code"/>
                </NavigationProperty>
            </EntityType>
            <EntityType Name="ActivationStatusType">
                <Key>
                    <PropertyRef Name="code"/>
                </Key>
                <Property Name="name" Type="Edm.String" MaxLength="255"/>
                <Property Name="descr" Type="Edm.String" MaxLength="1000"/>
                <Property Name="code" Type="Edm.String" MaxLength="20" Nullable="false"/>
                <NavigationProperty Name="texts" Type="Collection(SurveyService.ActivationStatusType_texts)">
                    <OnDelete Action="Cascade"/>
                </NavigationProperty>
                <NavigationProperty Name="localized" Type="SurveyService.ActivationStatusType_texts">
                    <ReferentialConstraint Property="code" ReferencedProperty="code"/>
                </NavigationProperty>
            </EntityType>
            <EntityType Name="FilledStatusType">
                <Key>
                    <PropertyRef Name="code"/>
                </Key>
                <Property Name="name" Type="Edm.String" MaxLength="255"/>
                <Property Name="descr" Type="Edm.String" MaxLength="1000"/>
                <Property Name="code" Type="Edm.String" MaxLength="20" Nullable="false"/>
                <NavigationProperty Name="texts" Type="Collection(SurveyService.FilledStatusType_texts)">
                    <OnDelete Action="Cascade"/>
                </NavigationProperty>
                <NavigationProperty Name="localized" Type="SurveyService.FilledStatusType_texts">
                    <ReferentialConstraint Property="code" ReferencedProperty="code"/>
                </NavigationProperty>
            </EntityType>
            <EntityType Name="DraftAdministrativeData">
                <Key>
                    <PropertyRef Name="DraftUUID"/>
                </Key>
                <Property Name="DraftUUID" Type="Edm.Guid" Nullable="false"/>
                <Property Name="CreationDateTime" Type="Edm.DateTimeOffset" Precision="7"/>
                <Property Name="CreatedByUser" Type="Edm.String" MaxLength="256"/>
                <Property Name="DraftIsCreatedByMe" Type="Edm.Boolean"/>
                <Property Name="LastChangeDateTime" Type="Edm.DateTimeOffset" Precision="7"/>
                <Property Name="LastChangedByUser" Type="Edm.String" MaxLength="256"/>
                <Property Name="InProcessByUser" Type="Edm.String" MaxLength="256"/>
                <Property Name="DraftIsProcessedByMe" Type="Edm.Boolean"/>
            </EntityType>
            <EntityType Name="QuestionType_texts">
                <Key>
                    <PropertyRef Name="locale"/>
                    <PropertyRef Name="code"/>
                </Key>
                <Property Name="locale" Type="Edm.String" MaxLength="14" Nullable="false"/>
                <Property Name="name" Type="Edm.String" MaxLength="255"/>
                <Property Name="descr" Type="Edm.String" MaxLength="1000"/>
                <Property Name="code" Type="Edm.String" MaxLength="20" Nullable="false"/>
            </EntityType>
            <EntityType Name="ActivationStatusType_texts">
                <Key>
                    <PropertyRef Name="locale"/>
                    <PropertyRef Name="code"/>
                </Key>
                <Property Name="locale" Type="Edm.String" MaxLength="14" Nullable="false"/>
                <Property Name="name" Type="Edm.String" MaxLength="255"/>
                <Property Name="descr" Type="Edm.String" MaxLength="1000"/>
                <Property Name="code" Type="Edm.String" MaxLength="20" Nullable="false"/>
            </EntityType>
            <EntityType Name="FilledStatusType_texts">
                <Key>
                    <PropertyRef Name="locale"/>
                    <PropertyRef Name="code"/>
                </Key>
                <Property Name="locale" Type="Edm.String" MaxLength="14" Nullable="false"/>
                <Property Name="name" Type="Edm.String" MaxLength="255"/>
                <Property Name="descr" Type="Edm.String" MaxLength="1000"/>
                <Property Name="code" Type="Edm.String" MaxLength="20" Nullable="false"/>
            </EntityType>
            <Action Name="draftPrepare" IsBound="true" EntitySetPath="in">
                <Parameter Name="in" Type="SurveyService.Questions"/>
                <Parameter Name="SideEffectsQualifier" Type="Edm.String"/>
                <ReturnType Type="SurveyService.Questions"/>
            </Action>
            <Action Name="draftPrepare" IsBound="true" EntitySetPath="in">
                <Parameter Name="in" Type="SurveyService.Options"/>
                <Parameter Name="SideEffectsQualifier" Type="Edm.String"/>
                <ReturnType Type="SurveyService.Options"/>
            </Action>
            <Action Name="draftPrepare" IsBound="true" EntitySetPath="in">
                <Parameter Name="in" Type="SurveyService.SurveyForms"/>
                <Parameter Name="SideEffectsQualifier" Type="Edm.String"/>
                <ReturnType Type="SurveyService.SurveyForms"/>
            </Action>
            <Action Name="draftActivate" IsBound="true" EntitySetPath="in">
                <Parameter Name="in" Type="SurveyService.SurveyForms"/>
                <ReturnType Type="SurveyService.SurveyForms"/>
            </Action>
            <Action Name="draftEdit" IsBound="true" EntitySetPath="in">
                <Parameter Name="in" Type="SurveyService.SurveyForms"/>
                <Parameter Name="PreserveChanges" Type="Edm.Boolean"/>
                <ReturnType Type="SurveyService.SurveyForms"/>
            </Action>
            <Annotations Target="SurveyService.Questions">
                <Annotation Term="UI.HeaderInfo">
                    <Record Type="UI.HeaderInfoType">
                        <PropertyValue Property="TypeName" String="Question"/>
                        <PropertyValue Property="TypeNamePlural" String="Questions"/>
                        <PropertyValue Property="Title">
                            <Record Type="UI.DataField">
                                <PropertyValue Property="Value" Path="question_no"/>
                            </Record>
                        </PropertyValue>
                        <PropertyValue Property="Description">
                            <Record Type="UI.DataField">
                                <PropertyValue Property="Value" Path="question_label"/>
                            </Record>
                        </PropertyValue>
                    </Record>
                </Annotation>
                <Annotation Term="UI.SelectionFields">
                    <Collection/>
                </Annotation>
                <Annotation Term="UI.PresentationVariant">
                    <Record Type="UI.PresentationVariantType">
                        <PropertyValue Property="SortOrder">
                            <Collection>
                                <Record Type="Common.SortOrderType">
                                    <PropertyValue Property="Property" PropertyPath="question_no"/>
                                    <PropertyValue Property="Descending" Bool="false"/>
                                </Record>
                            </Collection>
                        </PropertyValue>
                        <PropertyValue Property="Visualizations">
                            <Collection>
                                <AnnotationPath>@UI.LineItem</AnnotationPath>
                            </Collection>
                        </PropertyValue>
                    </Record>
                </Annotation>
                <Annotation Term="UI.LineItem">
                    <Collection>
                        <Record Type="UI.DataField">
                            <PropertyValue Property="Value" Path="question_no"/>
                            <PropertyValue Property="Label" String="Sequence No."/>
                        </Record>
                        <Record Type="UI.DataField">
                            <PropertyValue Property="Value" Path="question_label"/>
                            <PropertyValue Property="Label" String="Question"/>
                        </Record>
                        <Record Type="UI.DataField">
                            <PropertyValue Property="Value" Path="question_type_code"/>
                            <PropertyValue Property="Label" String="Question Type"/>
                        </Record>
                    </Collection>
                </Annotation>
                <Annotation Term="UI.Facets">
                    <Collection>
                        <Record Type="UI.ReferenceFacet">
                            <PropertyValue Property="Label" String="Options"/>
                            <PropertyValue Property="Target" AnnotationPath="options/@UI.LineItem"/>
                            <PropertyValue Property="ID" String="options"/>
                        </Record>
                    </Collection>
                </Annotation>
            </Annotations>
            <Annotations Target="SurveyService.EntityContainer/Questions">
                <Annotation Term="UI.PresentationVariant">
                    <Record Type="UI.PresentationVariantType">
                        <PropertyValue Property="SortOrder">
                            <Collection>
                                <Record Type="Common.SortOrderType">
                                    <PropertyValue Property="Property" PropertyPath="question_no"/>
                                    <PropertyValue Property="Descending" Bool="false"/>
                                </Record>
                            </Collection>
                        </PropertyValue>
                        <PropertyValue Property="Visualizations">
                            <Collection>
                                <AnnotationPath>@UI.LineItem</AnnotationPath>
                            </Collection>
                        </PropertyValue>
                    </Record>
                </Annotation>
                <Annotation Term="Common.DraftNode">
                    <Record Type="Common.DraftNodeType">
                        <PropertyValue Property="PreparationAction" String="SurveyService.draftPrepare"/>
                    </Record>
                </Annotation>
            </Annotations>
            <Annotations Target="SurveyService.Questions/createdAt">
                <Annotation Term="UI.HiddenFilter" Bool="true"/>
                <Annotation Term="Core.Immutable" Bool="true"/>
                <Annotation Term="Core.Computed" Bool="true"/>
                <Annotation Term="Common.Label" String="Created On"/>
            </Annotations>
            <Annotations Target="SurveyService.Questions/createdBy">
                <Annotation Term="UI.HiddenFilter" Bool="true"/>
                <Annotation Term="Core.Immutable" Bool="true"/>
                <Annotation Term="Core.Computed" Bool="true"/>
                <Annotation Term="Core.Description" String="User's unique ID"/>
                <Annotation Term="Common.Label" String="Created By"/>
            </Annotations>
            <Annotations Target="SurveyService.Questions/modifiedAt">
                <Annotation Term="UI.HiddenFilter" Bool="true"/>
                <Annotation Term="Core.Computed" Bool="true"/>
                <Annotation Term="Common.Label" String="Changed On"/>
            </Annotations>
            <Annotations Target="SurveyService.Questions/modifiedBy">
                <Annotation Term="UI.HiddenFilter" Bool="true"/>
                <Annotation Term="Core.Computed" Bool="true"/>
                <Annotation Term="Core.Description" String="User's unique ID"/>
                <Annotation Term="Common.Label" String="Changed By"/>
            </Annotations>
            <Annotations Target="SurveyService.Questions/ID">
                <Annotation Term="Core.Computed" Bool="true"/>
            </Annotations>
            <Annotations Target="SurveyService.Questions/question_no">
                <Annotation Term="Common.Label" String="Question No"/>
            </Annotations>
            <Annotations Target="SurveyService.Questions/question_label">
                <Annotation Term="Common.Label" String="Question"/>
            </Annotations>
            <Annotations Target="SurveyService.Questions/question_type">
                <Annotation Term="Common.Label" String="Question Type"/>
            </Annotations>
            <Annotations Target="SurveyService.Questions/question_type_code">
                <Annotation Term="Common.Text" Path="question_type/name">
                    <Annotation Term="UI.TextArrangement" EnumMember="UI.TextArrangementType/TextOnly"/>
                </Annotation>
                <Annotation Term="Common.ValueListWithFixedValues" Bool="true"/>
                <Annotation Term="Common.Label" String="Question Type"/>
                <Annotation Term="Common.ValueList">
                    <Record Type="Common.ValueListType">
                        <PropertyValue Property="Label" String="Question Type"/>
                        <PropertyValue Property="CollectionPath" String="QuestionType"/>
                        <PropertyValue Property="Parameters">
                            <Collection>
                                <Record Type="Common.ValueListParameterInOut">
                                    <PropertyValue Property="LocalDataProperty" PropertyPath="question_type_code"/>
                                    <PropertyValue Property="ValueListProperty" String="code"/>
                                </Record>
                                <Record Type="Common.ValueListParameterDisplayOnly">
                                    <PropertyValue Property="ValueListProperty" String="name"/>
                                </Record>
                            </Collection>
                        </PropertyValue>
                    </Record>
                </Annotation>
            </Annotations>
            <Annotations Target="SurveyService.Questions/surveyForm_ID">
                <Annotation Term="Common.ValueList">
                    <Record Type="Common.ValueListType">
                        <PropertyValue Property="Label" String="SurveyForms"/>
                        <PropertyValue Property="CollectionPath" String="SurveyForms"/>
                        <PropertyValue Property="Parameters">
                            <Collection>
                                <Record Type="Common.ValueListParameterInOut">
                                    <PropertyValue Property="LocalDataProperty" PropertyPath="surveyForm_ID"/>
                                    <PropertyValue Property="ValueListProperty" String="ID"/>
                                </Record>
                            </Collection>
                        </PropertyValue>
                    </Record>
                </Annotation>
            </Annotations>
            <Annotations Target="SurveyService.Questions/IsActiveEntity">
                <Annotation Term="UI.Hidden" Bool="true"/>
            </Annotations>
            <Annotations Target="SurveyService.Questions/HasActiveEntity">
                <Annotation Term="UI.Hidden" Bool="true"/>
            </Annotations>
            <Annotations Target="SurveyService.Questions/HasDraftEntity">
                <Annotation Term="UI.Hidden" Bool="true"/>
            </Annotations>
            <Annotations Target="SurveyService.Questions/DraftAdministrativeData">
                <Annotation Term="UI.Hidden" Bool="true"/>
            </Annotations>
            <Annotations Target="SurveyService.Options">
                <Annotation Term="UI.HeaderInfo">
                    <Record Type="UI.HeaderInfoType">
                        <PropertyValue Property="TypeName" String="Option"/>
                        <PropertyValue Property="TypeNamePlural" String="Options"/>
                        <PropertyValue Property="Title">
                            <Record Type="UI.DataField">
                                <PropertyValue Property="Value" String="Form Name"/>
                            </Record>
                        </PropertyValue>
                        <PropertyValue Property="Description">
                            <Record Type="UI.DataField">
                                <PropertyValue Property="Value" Path="question/question_label"/>
                            </Record>
                        </PropertyValue>
                    </Record>
                </Annotation>
                <Annotation Term="UI.SelectionFields">
                    <Collection/>
                </Annotation>
                <Annotation Term="UI.LineItem">
                    <Collection>
                        <Record Type="UI.DataField">
                            <PropertyValue Property="Value" Path="option_label"/>
                            <PropertyValue Property="Label" String="Options"/>
                        </Record>
                    </Collection>
                </Annotation>
                <Annotation Term="UI.Facets">
                    <Collection/>
                </Annotation>
            </Annotations>
            <Annotations Target="SurveyService.EntityContainer/Options">
                <Annotation Term="Common.DraftNode">
                    <Record Type="Common.DraftNodeType">
                        <PropertyValue Property="PreparationAction" String="SurveyService.draftPrepare"/>
                    </Record>
                </Annotation>
            </Annotations>
            <Annotations Target="SurveyService.Options/createdAt">
                <Annotation Term="UI.HiddenFilter" Bool="true"/>
                <Annotation Term="Core.Immutable" Bool="true"/>
                <Annotation Term="Core.Computed" Bool="true"/>
                <Annotation Term="Common.Label" String="Created On"/>
            </Annotations>
            <Annotations Target="SurveyService.Options/createdBy">
                <Annotation Term="UI.HiddenFilter" Bool="true"/>
                <Annotation Term="Core.Immutable" Bool="true"/>
                <Annotation Term="Core.Computed" Bool="true"/>
                <Annotation Term="Core.Description" String="User's unique ID"/>
                <Annotation Term="Common.Label" String="Created By"/>
            </Annotations>
            <Annotations Target="SurveyService.Options/modifiedAt">
                <Annotation Term="UI.HiddenFilter" Bool="true"/>
                <Annotation Term="Core.Computed" Bool="true"/>
                <Annotation Term="Common.Label" String="Changed On"/>
            </Annotations>
            <Annotations Target="SurveyService.Options/modifiedBy">
                <Annotation Term="UI.HiddenFilter" Bool="true"/>
                <Annotation Term="Core.Computed" Bool="true"/>
                <Annotation Term="Core.Description" String="User's unique ID"/>
                <Annotation Term="Common.Label" String="Changed By"/>
            </Annotations>
            <Annotations Target="SurveyService.Options/option_label">
                <Annotation Term="Common.Label" String="Option"/>
            </Annotations>
            <Annotations Target="SurveyService.Options/option_no">
                <Annotation Term="Common.Label" String="Option No"/>
            </Annotations>
            <Annotations Target="SurveyService.Options/IsActiveEntity">
                <Annotation Term="UI.Hidden" Bool="true"/>
            </Annotations>
            <Annotations Target="SurveyService.Options/HasActiveEntity">
                <Annotation Term="UI.Hidden" Bool="true"/>
            </Annotations>
            <Annotations Target="SurveyService.Options/HasDraftEntity">
                <Annotation Term="UI.Hidden" Bool="true"/>
            </Annotations>
            <Annotations Target="SurveyService.Options/DraftAdministrativeData">
                <Annotation Term="UI.Hidden" Bool="true"/>
            </Annotations>
            <Annotations Target="SurveyService.Answers/createdAt">
                <Annotation Term="UI.HiddenFilter" Bool="true"/>
                <Annotation Term="Core.Immutable" Bool="true"/>
                <Annotation Term="Core.Computed" Bool="true"/>
                <Annotation Term="Common.Label" String="Created On"/>
            </Annotations>
            <Annotations Target="SurveyService.Answers/createdBy">
                <Annotation Term="UI.HiddenFilter" Bool="true"/>
                <Annotation Term="Core.Immutable" Bool="true"/>
                <Annotation Term="Core.Computed" Bool="true"/>
                <Annotation Term="Core.Description" String="User's unique ID"/>
                <Annotation Term="Common.Label" String="Created By"/>
            </Annotations>
            <Annotations Target="SurveyService.Answers/modifiedAt">
                <Annotation Term="UI.HiddenFilter" Bool="true"/>
                <Annotation Term="Core.Computed" Bool="true"/>
                <Annotation Term="Common.Label" String="Changed On"/>
            </Annotations>
            <Annotations Target="SurveyService.Answers/modifiedBy">
                <Annotation Term="UI.HiddenFilter" Bool="true"/>
                <Annotation Term="Core.Computed" Bool="true"/>
                <Annotation Term="Core.Description" String="User's unique ID"/>
                <Annotation Term="Common.Label" String="Changed By"/>
            </Annotations>
            <Annotations Target="SurveyService.Answers/answer">
                <Annotation Term="Common.Label" String="Answer"/>
            </Annotations>
            <Annotations Target="SurveyService.Responses">
                <Annotation Term="UI.HeaderInfo">
                    <Record Type="UI.HeaderInfoType">
                        <PropertyValue Property="TypeName" String="Survey Form"/>
                        <PropertyValue Property="TypeNamePlural" String="Survey Forms"/>
                        <PropertyValue Property="Title">
                            <Record Type="UI.DataField">
                                <PropertyValue Property="Label" String="Status"/>
                                <PropertyValue Property="Value" Path="surveyFormInstance/filled_status/name"/>
                            </Record>
                        </PropertyValue>
                        <PropertyValue Property="Description">
                            <Record Type="UI.DataField">
                                <PropertyValue Property="Label" String="Survey Form"/>
                                <PropertyValue Property="Value" Path="surveyFormInstance/ID"/>
                            </Record>
                        </PropertyValue>
                    </Record>
                </Annotation>
                <Annotation Term="UI.SelectionFields">
                    <Collection>
                        <PropertyPath>surveyFormInstance/region/region_name</PropertyPath>
                        <PropertyPath>surveyFormInstance/customer/customer_id</PropertyPath>
                        <PropertyPath>surveyFormInstance/customer/customer_name</PropertyPath>
                        <PropertyPath>surveyFormInstance/customer_email</PropertyPath>
                        <PropertyPath>surveyFormInstance/surveyForm/survey_form_name</PropertyPath>
                        <PropertyPath>surveyFormInstance/filled_status_code</PropertyPath>
                    </Collection>
                </Annotation>
                <Annotation Term="UI.LineItem">
                    <Collection>
                        <Record Type="UI.DataField">
                            <PropertyValue Property="Value" Path="surveyFormInstance_ID"/>
                            <PropertyValue Property="Label" String="Survey Form"/>
                        </Record>
                        <Record Type="UI.DataField">
                            <PropertyValue Property="Value" Path="surveyFormInstance/region/region_name"/>
                            <PropertyValue Property="Label" String="Region"/>
                        </Record>
                        <Record Type="UI.DataField">
                            <PropertyValue Property="Value" Path="surveyFormInstance/customer/customer_id"/>
                            <PropertyValue Property="Label" String="Customer No"/>
                        </Record>
                        <Record Type="UI.DataField">
                            <PropertyValue Property="Value" Path="surveyFormInstance/customer/customer_name"/>
                            <PropertyValue Property="Label" String="Customer Name"/>
                        </Record>
                        <Record Type="UI.DataField">
                            <PropertyValue Property="Value" Path="surveyFormInstance/customer_email"/>
                            <PropertyValue Property="Label" String="Customer Email"/>
                        </Record>
                        <Record Type="UI.DataField">
                            <PropertyValue Property="Value" Path="surveyFormInstance/filled_status/name"/>
                            <PropertyValue Property="Label" String="Status"/>
                        </Record>
                        <Record Type="UI.DataField">
                            <PropertyValue Property="Value" Path="surveyFormInstance/expiry_date"/>
                            <PropertyValue Property="Label" String="Expiry Date"/>
                        </Record>
                        <Record Type="UI.DataField">
                            <PropertyValue Property="Value" Path="surveyFormInstance/reminder_interval"/>
                            <PropertyValue Property="Label" String="Reminder(In Days)"/>
                        </Record>
                        <Record Type="UI.DataField">
                            <PropertyValue Property="Value" Path="surveyFormInstance/surveyForm/survey_form_name"/>
                            <PropertyValue Property="Label" String="Form Template"/>
                        </Record>
                        <Record Type="UI.DataField">
                            <PropertyValue Property="Value" Path="surveyFormInstance/surveyForm/survey_form_version"/>
                            <PropertyValue Property="Label" String="Version"/>
                        </Record>
                        <Record Type="UI.DataFieldWithUrl">
                            <PropertyValue Property="Label" String="Response"/>
                            <PropertyValue Property="Value" Path="ID"/>
                            <PropertyValue Property="Url">
                                <Apply Function="odata.concat">
                                    <String>https://survey-form-customer-persona-insightful-wombat-gb.cfapps.ap10.hana.ondemand.com/?id=</String>
                                    <Path>ID</Path>
                                </Apply>
                            </PropertyValue>
                        </Record>
                    </Collection>
                </Annotation>
                <Annotation Term="UI.Facets">
                    <Collection>
                        <Record Type="UI.ReferenceFacet">
                            <PropertyValue Property="Label" String="General Details"/>
                            <PropertyValue Property="Target" AnnotationPath="@UI.FieldGroup#General"/>
                            <PropertyValue Property="ID" String="general"/>
                        </Record>
                        <Record Type="UI.ReferenceFacet">
                            <PropertyValue Property="Label" String="Form Details"/>
                            <PropertyValue Property="Target" AnnotationPath="@UI.FieldGroup#Form"/>
                            <PropertyValue Property="ID" String="form"/>
                        </Record>
                        <Record Type="UI.ReferenceFacet">
                            <PropertyValue Property="Label" String="Additional Details"/>
                            <PropertyValue Property="Target" AnnotationPath="@UI.FieldGroup#Addition"/>
                            <PropertyValue Property="ID" String="addition"/>
                        </Record>
                    </Collection>
                </Annotation>
                <Annotation Term="UI.FieldGroup" Qualifier="General">
                    <Record Type="UI.FieldGroupType">
                        <PropertyValue Property="Data">
                            <Collection>
                                <Record Type="UI.DataField">
                                    <PropertyValue Property="Value" Path="createdBy"/>
                                    <PropertyValue Property="Label" String="Created By"/>
                                </Record>
                                <Record Type="UI.DataField">
                                    <PropertyValue Property="Value" Path="createdAt"/>
                                    <PropertyValue Property="Label" String="Created At"/>
                                </Record>
                                <Record Type="UI.DataField">
                                    <PropertyValue Property="Value" Path="modifiedBy"/>
                                    <PropertyValue Property="Label" String="Modified By"/>
                                </Record>
                                <Record Type="UI.DataField">
                                    <PropertyValue Property="Value" Path="modifiedAt"/>
                                    <PropertyValue Property="Label" String="Modified At"/>
                                </Record>
                            </Collection>
                        </PropertyValue>
                    </Record>
                </Annotation>
                <Annotation Term="UI.FieldGroup" Qualifier="Form">
                    <Record Type="UI.FieldGroupType">
                        <PropertyValue Property="Data">
                            <Collection>
                                <Record Type="UI.DataField">
                                    <PropertyValue Property="Value" Path="surveyFormInstance/region/region_name"/>
                                    <PropertyValue Property="Label" String="Region"/>
                                </Record>
                                <Record Type="UI.DataField">
                                    <PropertyValue Property="Value" Path="surveyFormInstance/customer/customer_id"/>
                                    <PropertyValue Property="Label" String="Customer No"/>
                                </Record>
                                <Record Type="UI.DataField">
                                    <PropertyValue Property="Value" Path="surveyFormInstance/customer/customer_name"/>
                                    <PropertyValue Property="Label" String="Customer Name"/>
                                </Record>
                                <Record Type="UI.DataField">
                                    <PropertyValue Property="Value" Path="surveyFormInstance/customer_email"/>
                                    <PropertyValue Property="Label" String="Customer Email"/>
                                </Record>
                                <Record Type="UI.DataField">
                                    <PropertyValue Property="Value" Path="surveyFormInstance/expiry_date"/>
                                    <PropertyValue Property="Label" String="Expiry Date"/>
                                </Record>
                                <Record Type="UI.DataField">
                                    <PropertyValue Property="Value" Path="surveyFormInstance/reminder_interval"/>
                                    <PropertyValue Property="Label" String="Reminder(In Days)"/>
                                </Record>
                            </Collection>
                        </PropertyValue>
                    </Record>
                </Annotation>
                <Annotation Term="UI.FieldGroup" Qualifier="Addition">
                    <Record Type="UI.FieldGroupType">
                        <PropertyValue Property="Data">
                            <Collection>
                                <Record Type="UI.DataField">
                                    <PropertyValue Property="Value" Path="surveyFormInstance/surveyForm/survey_form_name"/>
                                    <PropertyValue Property="Label" String="Form Template"/>
                                </Record>
                                <Record Type="UI.DataField">
                                    <PropertyValue Property="Value" Path="surveyFormInstance/surveyForm/survey_form_version"/>
                                    <PropertyValue Property="Label" String="Version"/>
                                </Record>
                                <Record Type="UI.DataFieldWithUrl">
                                    <PropertyValue Property="Label" String="Response"/>
                                    <PropertyValue Property="Value" String="View Survey Form"/>
                                    <PropertyValue Property="Url">
                                        <Apply Function="odata.concat">
                                            <String>https://survey-form-customer-persona-insightful-wombat-gb.cfapps.ap10.hana.ondemand.com/?id=</String>
                                            <Path>ID</Path>
                                        </Apply>
                                    </PropertyValue>
                                </Record>
                            </Collection>
                        </PropertyValue>
                    </Record>
                </Annotation>
            </Annotations>
            <Annotations Target="SurveyService.Responses/createdAt">
                <Annotation Term="UI.HiddenFilter" Bool="true"/>
                <Annotation Term="Core.Immutable" Bool="true"/>
                <Annotation Term="Core.Computed" Bool="true"/>
                <Annotation Term="Common.Label" String="Created On"/>
            </Annotations>
            <Annotations Target="SurveyService.Responses/createdBy">
                <Annotation Term="UI.HiddenFilter" Bool="true"/>
                <Annotation Term="Core.Immutable" Bool="true"/>
                <Annotation Term="Core.Computed" Bool="true"/>
                <Annotation Term="Core.Description" String="User's unique ID"/>
                <Annotation Term="Common.Label" String="Created By"/>
            </Annotations>
            <Annotations Target="SurveyService.Responses/modifiedAt">
                <Annotation Term="UI.HiddenFilter" Bool="true"/>
                <Annotation Term="Core.Computed" Bool="true"/>
                <Annotation Term="Common.Label" String="Changed On"/>
            </Annotations>
            <Annotations Target="SurveyService.Responses/modifiedBy">
                <Annotation Term="UI.HiddenFilter" Bool="true"/>
                <Annotation Term="Core.Computed" Bool="true"/>
                <Annotation Term="Core.Description" String="User's unique ID"/>
                <Annotation Term="Common.Label" String="Changed By"/>
            </Annotations>
            <Annotations Target="SurveyService.SurveyForms">
                <Annotation Term="UI.HeaderInfo">
                    <Record Type="UI.HeaderInfoType">
                        <PropertyValue Property="TypeName" String="SurveyForm"/>
                        <PropertyValue Property="TypeNamePlural" String="SurveyForms"/>
                        <PropertyValue Property="Title">
                            <Record Type="UI.DataField">
                                <PropertyValue Property="Value" Path="survey_form_name"/>
                            </Record>
                        </PropertyValue>
                    </Record>
                </Annotation>
                <Annotation Term="UI.SelectionFields">
                    <Collection>
                        <PropertyPath>survey_form_name</PropertyPath>
                        <PropertyPath>activation_status_code</PropertyPath>
                    </Collection>
                </Annotation>
                <Annotation Term="UI.LineItem">
                    <Collection>
                        <Record Type="UI.DataField">
                            <PropertyValue Property="Value" Path="survey_form_name"/>
                            <PropertyValue Property="Label" String="Form Name"/>
                        </Record>
                        <Record Type="UI.DataField">
                            <PropertyValue Property="Value" Path="survey_form_version"/>
                            <PropertyValue Property="Label" String="Version"/>
                        </Record>
                        <Record Type="UI.DataField">
                            <PropertyValue Property="Value" Path="activation_status/name"/>
                            <PropertyValue Property="Label" String="Status"/>
                        </Record>
                    </Collection>
                </Annotation>
                <Annotation Term="UI.Facets">
                    <Collection>
                        <Record Type="UI.ReferenceFacet">
                            <PropertyValue Property="Label" String="Form Details"/>
                            <PropertyValue Property="Target" AnnotationPath="@UI.FieldGroup#Forms"/>
                            <PropertyValue Property="ID" String="forms"/>
                        </Record>
                        <Record Type="UI.ReferenceFacet">
                            <PropertyValue Property="Label" String="Questions"/>
                            <PropertyValue Property="Target" AnnotationPath="Questions/@UI.LineItem"/>
                            <PropertyValue Property="ID" String="questions"/>
                        </Record>
                    </Collection>
                </Annotation>
                <Annotation Term="UI.FieldGroup" Qualifier="Forms">
                    <Record Type="UI.FieldGroupType">
                        <PropertyValue Property="Data">
                            <Collection>
                                <Record Type="UI.DataField">
                                    <PropertyValue Property="Value" Path="survey_form_name"/>
                                    <PropertyValue Property="Label" String="Form Name"/>
                                </Record>
                                <Record Type="UI.DataField">
                                    <PropertyValue Property="Value" Path="survey_form_version"/>
                                    <PropertyValue Property="Label" String="Version"/>
                                </Record>
                                <Record Type="UI.DataField">
                                    <PropertyValue Property="Value" Path="activation_status_code"/>
                                    <PropertyValue Property="Label" String="Status"/>
                                </Record>
                            </Collection>
                        </PropertyValue>
                    </Record>
                </Annotation>
            </Annotations>
            <Annotations Target="SurveyService.EntityContainer/SurveyForms">
                <Annotation Term="Common.DraftRoot">
                    <Record Type="Common.DraftRootType">
                        <PropertyValue Property="ActivationAction" String="SurveyService.draftActivate"/>
                        <PropertyValue Property="EditAction" String="SurveyService.draftEdit"/>
                        <PropertyValue Property="PreparationAction" String="SurveyService.draftPrepare"/>
                    </Record>
                </Annotation>
            </Annotations>
            <Annotations Target="SurveyService.SurveyForms/createdAt">
                <Annotation Term="UI.HiddenFilter" Bool="true"/>
                <Annotation Term="Core.Immutable" Bool="true"/>
                <Annotation Term="Core.Computed" Bool="true"/>
                <Annotation Term="Common.Label" String="Created On"/>
            </Annotations>
            <Annotations Target="SurveyService.SurveyForms/createdBy">
                <Annotation Term="UI.HiddenFilter" Bool="true"/>
                <Annotation Term="Core.Immutable" Bool="true"/>
                <Annotation Term="Core.Computed" Bool="true"/>
                <Annotation Term="Core.Description" String="User's unique ID"/>
                <Annotation Term="Common.Label" String="Created By"/>
            </Annotations>
            <Annotations Target="SurveyService.SurveyForms/modifiedAt">
                <Annotation Term="UI.HiddenFilter" Bool="true"/>
                <Annotation Term="Core.Computed" Bool="true"/>
                <Annotation Term="Common.Label" String="Changed On"/>
            </Annotations>
            <Annotations Target="SurveyService.SurveyForms/modifiedBy">
                <Annotation Term="UI.HiddenFilter" Bool="true"/>
                <Annotation Term="Core.Computed" Bool="true"/>
                <Annotation Term="Core.Description" String="User's unique ID"/>
                <Annotation Term="Common.Label" String="Changed By"/>
            </Annotations>
            <Annotations Target="SurveyService.SurveyForms/ID">
                <Annotation Term="Core.Computed" Bool="true"/>
            </Annotations>
            <Annotations Target="SurveyService.SurveyForms/survey_form_name">
                <Annotation Term="Common.Label" String="Form Name"/>
            </Annotations>
            <Annotations Target="SurveyService.SurveyForms/survey_form_version">
                <Annotation Term="Common.Label" String="Form Version"/>
            </Annotations>
            <Annotations Target="SurveyService.SurveyForms/activation_status">
                <Annotation Term="Common.Label" String="Status"/>
            </Annotations>
            <Annotations Target="SurveyService.SurveyForms/activation_status_code">
                <Annotation Term="Common.Label" String="Status"/>
                <Annotation Term="Common.ValueList">
                    <Record Type="Common.ValueListType">
                        <PropertyValue Property="Label" String="Status"/>
                        <PropertyValue Property="CollectionPath" String="ActivationStatusType"/>
                        <PropertyValue Property="Parameters">
                            <Collection>
                                <Record Type="Common.ValueListParameterInOut">
                                    <PropertyValue Property="LocalDataProperty" PropertyPath="activation_status_code"/>
                                    <PropertyValue Property="ValueListProperty" String="code"/>
                                </Record>
                                <Record Type="Common.ValueListParameterDisplayOnly">
                                    <PropertyValue Property="ValueListProperty" String="name"/>
                                </Record>
                            </Collection>
                        </PropertyValue>
                    </Record>
                </Annotation>
            </Annotations>
            <Annotations Target="SurveyService.SurveyForms/IsActiveEntity">
                <Annotation Term="UI.Hidden" Bool="true"/>
            </Annotations>
            <Annotations Target="SurveyService.SurveyForms/HasActiveEntity">
                <Annotation Term="UI.Hidden" Bool="true"/>
            </Annotations>
            <Annotations Target="SurveyService.SurveyForms/HasDraftEntity">
                <Annotation Term="UI.Hidden" Bool="true"/>
            </Annotations>
            <Annotations Target="SurveyService.SurveyForms/DraftAdministrativeData">
                <Annotation Term="UI.Hidden" Bool="true"/>
            </Annotations>
            <Annotations Target="SurveyService.SurveyFormInstances">
                <Annotation Term="Common.Label" String="Survey Forms"/>
            </Annotations>
            <Annotations Target="SurveyService.SurveyFormInstances/ID">
                <Annotation Term="Common.Label" String="Survey Form"/>
            </Annotations>
            <Annotations Target="SurveyService.SurveyFormInstances/createdAt">
                <Annotation Term="UI.HiddenFilter" Bool="true"/>
                <Annotation Term="Core.Immutable" Bool="true"/>
                <Annotation Term="Core.Computed" Bool="true"/>
                <Annotation Term="Common.Label" String="Created On"/>
            </Annotations>
            <Annotations Target="SurveyService.SurveyFormInstances/createdBy">
                <Annotation Term="UI.HiddenFilter" Bool="true"/>
                <Annotation Term="Core.Immutable" Bool="true"/>
                <Annotation Term="Core.Computed" Bool="true"/>
                <Annotation Term="Core.Description" String="User's unique ID"/>
                <Annotation Term="Common.Label" String="Created By"/>
            </Annotations>
            <Annotations Target="SurveyService.SurveyFormInstances/modifiedAt">
                <Annotation Term="UI.HiddenFilter" Bool="true"/>
                <Annotation Term="Core.Computed" Bool="true"/>
                <Annotation Term="Common.Label" String="Changed On"/>
            </Annotations>
            <Annotations Target="SurveyService.SurveyFormInstances/modifiedBy">
                <Annotation Term="UI.HiddenFilter" Bool="true"/>
                <Annotation Term="Core.Computed" Bool="true"/>
                <Annotation Term="Core.Description" String="User's unique ID"/>
                <Annotation Term="Common.Label" String="Changed By"/>
            </Annotations>
            <Annotations Target="SurveyService.SurveyFormInstances/customer_email">
                <Annotation Term="Common.Label" String="Customer Email"/>
            </Annotations>
            <Annotations Target="SurveyService.SurveyFormInstances/expiry_date">
                <Annotation Term="Common.Label" String="Expiry Date"/>
            </Annotations>
            <Annotations Target="SurveyService.SurveyFormInstances/reminder_interval">
                <Annotation Term="Common.Label" String="Reminder"/>
            </Annotations>
            <Annotations Target="SurveyService.SurveyFormInstances/filled_status">
                <Annotation Term="Common.Label" String="Status"/>
            </Annotations>
            <Annotations Target="SurveyService.SurveyFormInstances/filled_status_code">
                <Annotation Term="Common.Text" Path="filled_status/name">
                    <Annotation Term="UI.TextArrangement" EnumMember="UI.TextArrangementType/TextOnly"/>
                </Annotation>
                <Annotation Term="Common.Label" String="Status"/>
                <Annotation Term="Common.ValueList">
                    <Record Type="Common.ValueListType">
                        <PropertyValue Property="Label" String="Status"/>
                        <PropertyValue Property="CollectionPath" String="FilledStatusType"/>
                        <PropertyValue Property="Parameters">
                            <Collection>
                                <Record Type="Common.ValueListParameterInOut">
                                    <PropertyValue Property="LocalDataProperty" PropertyPath="filled_status_code"/>
                                    <PropertyValue Property="ValueListProperty" String="code"/>
                                </Record>
                                <Record Type="Common.ValueListParameterDisplayOnly">
                                    <PropertyValue Property="ValueListProperty" String="name"/>
                                </Record>
                            </Collection>
                        </PropertyValue>
                    </Record>
                </Annotation>
            </Annotations>
            <Annotations Target="SurveyService.SurveyFormInstances/region_ID">
                <Annotation Term="Common.ValueList">
                    <Record Type="Common.ValueListType">
                        <PropertyValue Property="Label" String="Regions"/>
                        <PropertyValue Property="CollectionPath" String="Regions"/>
                        <PropertyValue Property="Parameters">
                            <Collection>
                                <Record Type="Common.ValueListParameterInOut">
                                    <PropertyValue Property="LocalDataProperty" PropertyPath="region_ID"/>
                                    <PropertyValue Property="ValueListProperty" String="ID"/>
                                </Record>
                            </Collection>
                        </PropertyValue>
                    </Record>
                </Annotation>
            </Annotations>
            <Annotations Target="SurveyService.SurveyFormInstances/customer_ID">
                <Annotation Term="Common.ValueList">
                    <Record Type="Common.ValueListType">
                        <PropertyValue Property="Label" String="Customers"/>
                        <PropertyValue Property="CollectionPath" String="Customers"/>
                        <PropertyValue Property="Parameters">
                            <Collection>
                                <Record Type="Common.ValueListParameterInOut">
                                    <PropertyValue Property="LocalDataProperty" PropertyPath="customer_ID"/>
                                    <PropertyValue Property="ValueListProperty" String="ID"/>
                                </Record>
                            </Collection>
                        </PropertyValue>
                    </Record>
                </Annotation>
            </Annotations>
            <Annotations Target="SurveyService.SurveyFormInstances/surveyForm_ID">
                <Annotation Term="Common.ValueList">
                    <Record Type="Common.ValueListType">
                        <PropertyValue Property="Label" String="SurveyForms"/>
                        <PropertyValue Property="CollectionPath" String="SurveyForms"/>
                        <PropertyValue Property="Parameters">
                            <Collection>
                                <Record Type="Common.ValueListParameterInOut">
                                    <PropertyValue Property="LocalDataProperty" PropertyPath="surveyForm_ID"/>
                                    <PropertyValue Property="ValueListProperty" String="ID"/>
                                </Record>
                            </Collection>
                        </PropertyValue>
                    </Record>
                </Annotation>
            </Annotations>
            <Annotations Target="SurveyService.Regions/createdAt">
                <Annotation Term="UI.HiddenFilter" Bool="true"/>
                <Annotation Term="Core.Immutable" Bool="true"/>
                <Annotation Term="Core.Computed" Bool="true"/>
                <Annotation Term="Common.Label" String="Created On"/>
            </Annotations>
            <Annotations Target="SurveyService.Regions/createdBy">
                <Annotation Term="UI.HiddenFilter" Bool="true"/>
                <Annotation Term="Core.Immutable" Bool="true"/>
                <Annotation Term="Core.Computed" Bool="true"/>
                <Annotation Term="Core.Description" String="User's unique ID"/>
                <Annotation Term="Common.Label" String="Created By"/>
            </Annotations>
            <Annotations Target="SurveyService.Regions/modifiedAt">
                <Annotation Term="UI.HiddenFilter" Bool="true"/>
                <Annotation Term="Core.Computed" Bool="true"/>
                <Annotation Term="Common.Label" String="Changed On"/>
            </Annotations>
            <Annotations Target="SurveyService.Regions/modifiedBy">
                <Annotation Term="UI.HiddenFilter" Bool="true"/>
                <Annotation Term="Core.Computed" Bool="true"/>
                <Annotation Term="Core.Description" String="User's unique ID"/>
                <Annotation Term="Common.Label" String="Changed By"/>
            </Annotations>
            <Annotations Target="SurveyService.Regions/region_name">
                <Annotation Term="Common.Label" String="Region"/>
            </Annotations>
            <Annotations Target="SurveyService.Customers/createdAt">
                <Annotation Term="UI.HiddenFilter" Bool="true"/>
                <Annotation Term="Core.Immutable" Bool="true"/>
                <Annotation Term="Core.Computed" Bool="true"/>
                <Annotation Term="Common.Label" String="Created On"/>
            </Annotations>
            <Annotations Target="SurveyService.Customers/createdBy">
                <Annotation Term="UI.HiddenFilter" Bool="true"/>
                <Annotation Term="Core.Immutable" Bool="true"/>
                <Annotation Term="Core.Computed" Bool="true"/>
                <Annotation Term="Core.Description" String="User's unique ID"/>
                <Annotation Term="Common.Label" String="Created By"/>
            </Annotations>
            <Annotations Target="SurveyService.Customers/modifiedAt">
                <Annotation Term="UI.HiddenFilter" Bool="true"/>
                <Annotation Term="Core.Computed" Bool="true"/>
                <Annotation Term="Common.Label" String="Changed On"/>
            </Annotations>
            <Annotations Target="SurveyService.Customers/modifiedBy">
                <Annotation Term="UI.HiddenFilter" Bool="true"/>
                <Annotation Term="Core.Computed" Bool="true"/>
                <Annotation Term="Core.Description" String="User's unique ID"/>
                <Annotation Term="Common.Label" String="Changed By"/>
            </Annotations>
            <Annotations Target="SurveyService.Customers/customer_id">
                <Annotation Term="Common.Label" String="Customer No"/>
            </Annotations>
            <Annotations Target="SurveyService.Customers/customer_name">
                <Annotation Term="Common.Label" String="Customer"/>
            </Annotations>
            <Annotations Target="SurveyService.Customers/region_ID">
                <Annotation Term="Common.ValueList">
                    <Record Type="Common.ValueListType">
                        <PropertyValue Property="Label" String="Regions"/>
                        <PropertyValue Property="CollectionPath" String="Regions"/>
                        <PropertyValue Property="Parameters">
                            <Collection>
                                <Record Type="Common.ValueListParameterInOut">
                                    <PropertyValue Property="LocalDataProperty" PropertyPath="region_ID"/>
                                    <PropertyValue Property="ValueListProperty" String="ID"/>
                                </Record>
                            </Collection>
                        </PropertyValue>
                    </Record>
                </Annotation>
            </Annotations>
            <Annotations Target="SurveyService.QuestionType">
                <Annotation Term="UI.Identification">
                    <Collection>
                        <Record Type="UI.DataField">
                            <PropertyValue Property="Value" Path="name"/>
                        </Record>
                    </Collection>
                </Annotation>
            </Annotations>
            <Annotations Target="SurveyService.QuestionType/name">
                <Annotation Term="Common.Label" String="Name"/>
            </Annotations>
            <Annotations Target="SurveyService.QuestionType/descr">
                <Annotation Term="Common.Label" String="Description"/>
            </Annotations>
            <Annotations Target="SurveyService.QuestionType/code">
                <Annotation Term="Common.Text" Path="name">
                    <Annotation Term="UI.TextArrangement" EnumMember="UI.TextArrangementType/TextOnly"/>
                </Annotation>
                <Annotation Term="Common.Label" String="Question Type"/>
            </Annotations>
            <Annotations Target="SurveyService.ActivationStatusType">
                <Annotation Term="UI.Identification">
                    <Collection>
                        <Record Type="UI.DataField">
                            <PropertyValue Property="Value" Path="name"/>
                        </Record>
                    </Collection>
                </Annotation>
            </Annotations>
            <Annotations Target="SurveyService.ActivationStatusType/name">
                <Annotation Term="Common.Label" String="Name"/>
            </Annotations>
            <Annotations Target="SurveyService.ActivationStatusType/descr">
                <Annotation Term="Common.Label" String="Description"/>
            </Annotations>
            <Annotations Target="SurveyService.FilledStatusType">
                <Annotation Term="UI.Identification">
                    <Collection>
                        <Record Type="UI.DataField">
                            <PropertyValue Property="Value" Path="name"/>
                        </Record>
                    </Collection>
                </Annotation>
            </Annotations>
            <Annotations Target="SurveyService.FilledStatusType/name">
                <Annotation Term="Common.Label" String="Name"/>
            </Annotations>
            <Annotations Target="SurveyService.FilledStatusType/descr">
                <Annotation Term="Common.Label" String="Description"/>
            </Annotations>
            <Annotations Target="SurveyService.DraftAdministrativeData">
                <Annotation Term="Common.Label" String="Draft Administrative Data"/>
            </Annotations>
            <Annotations Target="SurveyService.DraftAdministrativeData/DraftUUID">
                <Annotation Term="UI.Hidden" Bool="true"/>
                <Annotation Term="Common.Label" String="Draft (Technical ID)"/>
            </Annotations>
            <Annotations Target="SurveyService.DraftAdministrativeData/CreationDateTime">
                <Annotation Term="Common.Label" String="Draft Created On"/>
            </Annotations>
            <Annotations Target="SurveyService.DraftAdministrativeData/CreatedByUser">
                <Annotation Term="Common.Label" String="Draft Created By"/>
            </Annotations>
            <Annotations Target="SurveyService.DraftAdministrativeData/DraftIsCreatedByMe">
                <Annotation Term="UI.Hidden" Bool="true"/>
                <Annotation Term="Common.Label" String="Draft Created By Me"/>
            </Annotations>
            <Annotations Target="SurveyService.DraftAdministrativeData/LastChangeDateTime">
                <Annotation Term="Common.Label" String="Draft Last Changed On"/>
            </Annotations>
            <Annotations Target="SurveyService.DraftAdministrativeData/LastChangedByUser">
                <Annotation Term="Common.Label" String="Draft Last Changed By"/>
            </Annotations>
            <Annotations Target="SurveyService.DraftAdministrativeData/InProcessByUser">
                <Annotation Term="Common.Label" String="Draft In Process By"/>
            </Annotations>
            <Annotations Target="SurveyService.DraftAdministrativeData/DraftIsProcessedByMe">
                <Annotation Term="UI.Hidden" Bool="true"/>
                <Annotation Term="Common.Label" String="Draft In Process By Me"/>
            </Annotations>
            <Annotations Target="SurveyService.QuestionType_texts/name">
                <Annotation Term="Common.Label" String="Name"/>
            </Annotations>
            <Annotations Target="SurveyService.QuestionType_texts/descr">
                <Annotation Term="Common.Label" String="Description"/>
            </Annotations>
            <Annotations Target="SurveyService.ActivationStatusType_texts/name">
                <Annotation Term="Common.Label" String="Name"/>
            </Annotations>
            <Annotations Target="SurveyService.ActivationStatusType_texts/descr">
                <Annotation Term="Common.Label" String="Description"/>
            </Annotations>
            <Annotations Target="SurveyService.FilledStatusType_texts/name">
                <Annotation Term="Common.Label" String="Name"/>
            </Annotations>
            <Annotations Target="SurveyService.FilledStatusType_texts/descr">
                <Annotation Term="Common.Label" String="Description"/>
            </Annotations>
        </Schema>
    </edmx:DataServices>
</edmx:Edmx>